# 类文件结构

[TOC]

## 无关性的基石

“与平台无关”的理想最终实现在操作系统的应用层上：Sun公司以及其他虚拟机提供商发布了许多可以运行在各
种不同平台上的虚拟机，这些虚拟机都可以载入和执行同一种平台无关的字节码，从而实现了程序的“一次编写，到处运行”。

实现语言无关性的基础仍然是虚拟机和字节码存储格式。Java虚拟机不和包括Java在内的任何语言绑定，它只与“Class文件”这种特定的二进制文件格式所关联，Class文件中包含了Java虚拟机指令集和符号表以及若干其他辅助信息。基于安全方面的考虑，Java虚拟机规范要求在Class文件中使用许多强制性的语法和结构化约束，但任一门功能性语言都可以表示为一个能被Java虚拟机所接受的有效的Class文件。

字节码命令所能提供的语义描述能力肯定比Java语言本身更加强大。因此，有一些Java语言本身无法有效支持的语言特性不代表字节码本身无法支持，这也为其他语言实现一些有别于Java的语言特性提供了基础。

## Class类文件的结构

Class文件是一组以8位字节为基础单位的二进制流，各个数据项目严格按照顺序紧凑地排列在Class文件之中，中间没有添加任何分隔符，这使得整个Class文件中存储的内容几乎全部是程序运行的必要数据，没有空隙存在。当遇到需要占用8位字节以上空间的数据项时，则会按照高位在前的方式分割成若干个8位字节进行存储。

> 注意，任何一个Class文件都对应着唯一一个类或接口的定义信息，但反过来说，类或接口并不一定都得定义在文件里(譬如类或接口也可以通过类加载器直接生成)。

Class文件格式采用一种类似于C语言结构体的伪结构来存储数据，这种伪结构中只有两种数据类型：无符号数和表。

无符号数属于基本的数据类型，以u1、u2、u4、u8来分别代表1个字节、2个字节、4个字节和8个字节的无符号数；表是由多个无符号数或者其他表作为数据项构成的复合数据类型，所有表都习惯性地以“_info”结尾。表用于描述有层次关系的复合结构的数据，整个Class文件本质上就是一张表。

### 魔数与Class文件的版本

每个Class文件的头4个字节称为魔数(Magic Number)，它的唯一作用是确定这个文件是否为一个能被虚拟机接受的Class文件。很多文件存储标准中都使用魔数来进行身份识别，譬如图片格式，如gif或者jpeg等在文件头中都存有魔数。Class文件的魔数为`0xCAFEBABE`。

紧接着魔数的4个字节存储的是Class文件的版本号：第5和第6个字节是次版本号（Minor Version），第7和第8个字节是主版本号（Major Version）。Java的版本号是从45开始的，高版本的JDK能向下兼容以前版本的Class文件，但虚拟机拒绝执行超过其版本号的Class文件。

### 常量池

紧接着主次版本号之后的是常量池入口，常量池可以理解为Class文件之中的资源仓库。

由于常量池中常量的数量是不固定的，所以在常量池的入口需要放置一项u2类型的数据，代表常量池容量计数值(constant_pool_count)。这个容量计数是从1而不是0开始的，设计者将第0项常量空出来是有特殊考虑的,这样做的目的在于满足后面某些指向常量池的索引值的数据在特定情况下需要表达“不引用任何一个常量池项目”的含义，这种情况就可以把索引值置为0来表示。Class文件结构中只有常量池的容量计数是从1开始，对于其他集合类型，包括接口索引集合、字段表集合、方法表集合等的容量计数都与一般习惯相同，是从0开始的。

常量池中主要存放两大类常量：字面量(Literal)和符号引用(Symbolic References)。字面量比较接近于Java语言层面的常量概念，如文本字符串、声明为final的常量值等。符号引用包括了下面三类常量：

+ 类和接口的全限定名(Fully Qualified Name)
+ 字段的名称和描述符(Descriptor)
+ 方法的名称和描述符

Java代码在进行Javac编译的时候，并不像C和C++那样有“连接”这一步骤，而是在虚拟机加载Class文件的时候进行动态连接。也就是说,在Class文件中不会保存各个方法、字段的最终内存布局信息，因此这些字段、方法的符号引用不经过运行期转换的话无法得到真正的内存入口地址，也就无法直接被虚拟机使用。当虚拟机运行时，需要从常量池获得对应的符号引用，再在类创建时或运行时解析、翻译到具体的内存地址之中。

常量池中的每一项常量都是一个表，表开始的第一位是一个u1类型的标志位，代表当前这个常量属于哪种常量类型。

| 类型                             | 标志 | 描述                     |
| -------------------------------- | ---- | ------------------------ |
| CONSTANT_Utf8_info               | 1    | UTF-8编码的字符串        |
| CONSTANT_Integer_info            | 3    | 整型字面量               |
| CONSTANT_Float_info              | 4    | 浮点型字面量             |
| CONSTANT_Long_info               | 5    | 长整型字面量             |
| CONSTANT_Double_info             | 6    | 双精度浮点型字面量       |
| CONSTANT_Class_info              | 7    | 类或接口的符号引用       |
| CONSTANT_String_info             | 8    | 字符串类型字面量         |
| CONSTANT_Fieldref_info           | 9    | 字段的符号引用           |
| CONSTANT_Methodref_info          | 10   | 类中方法的符号引用       |
| CONSTANT_InterfaceMethodref_info | 11   | 接口中方法的符号引用     |
| CONSTANT_NameAndType_info        | 12   | 字段或方法的部分符号引用 |
| CONSTANT_MethodHandle_info       | 15   | 表示方法句柄             |
| CONSTANT_MethodType_info         | 16   | 标示方法类型             |
| CONSTANT_InvokeDynamic_info      | 18   | 表示一个动态方法的调用点 |

> 由于Class文件中方法、字段等都需要引用CONSTANT_Utf8_info型常量来描述名称，所以CONSTANT_Utf8_info型常量的最大长度也就是Java中方法、字段名的最大长度，即u2类型能表达的最大值65535，所以Java程序中若定义了超过64KB英文字符的变量或方法名，将无法编译。

在JDK的bin目录中，Oracle公司提供了工具：javap，使用`javap -verbose TestClass`可以输出`TestClass.class`文件字节码内容。

```shell
yikang@yikang-Inspiron-3558:$ javap -verbose TestClass.class 
Classfile /home/yikang/IdeaProjects/codePractice/out/production/codePractice/com/yikang/example/TestClass.class
  Last modified 2020-10-18; size 391 bytes
  MD5 checksum 6083424f875a25d22c7f23674576e2e4
  Compiled from "TestClass.java"
public class com.yikang.example.TestClass
  minor version: 0
  major version: 52
  flags: ACC_PUBLIC, ACC_SUPER
Constant pool:
   #1 = Methodref          #4.#18         // java/lang/Object."<init>":()V
   #2 = Fieldref           #3.#19         // com/yikang/example/TestClass.m:I
   #3 = Class              #20            // com/yikang/example/TestClass
   #4 = Class              #21            // java/lang/Object
   #5 = Utf8               m
   #6 = Utf8               I
   #7 = Utf8               <init>
   #8 = Utf8               ()V
   #9 = Utf8               Code
  #10 = Utf8               LineNumberTable
  #11 = Utf8               LocalVariableTable
  #12 = Utf8               this
  #13 = Utf8               Lcom/yikang/example/TestClass;
  #14 = Utf8               inc
  #15 = Utf8               ()I
  #16 = Utf8               SourceFile
  #17 = Utf8               TestClass.java
  #18 = NameAndType        #7:#8          // "<init>":()V
  #19 = NameAndType        #5:#6          // m:I
  #20 = Utf8               com/yikang/example/TestClass
  #21 = Utf8               java/lang/Object
{
  public com.yikang.example.TestClass();
    descriptor: ()V
    flags: ACC_PUBLIC
    Code:
      stack=1, locals=1, args_size=1
         0: aload_0
         1: invokespecial #1                  // Method java/lang/Object."<init>":()V
         4: return
      LineNumberTable:
        line 3: 0
      LocalVariableTable:
        Start  Length  Slot  Name   Signature
            0       5     0  this   Lcom/yikang/example/TestClass;

  public int inc();
    descriptor: ()I
    flags: ACC_PUBLIC
    Code:
      stack=2, locals=1, args_size=1
         0: aload_0
         1: getfield      #2                  // Field m:I
         4: iconst_1
         5: iadd
         6: ireturn
      LineNumberTable:
        line 7: 0
      LocalVariableTable:
        Start  Length  Slot  Name   Signature
            0       7     0  this   Lcom/yikang/example/TestClass;
}
SourceFile: "TestClass.java"

```

### 访问标志

在常量池结束之后，紧接着的两个字节代表访问标志(access_flags)，这个标志用于识别一些类或者接口层次的访问信息。

| 标志名称       | 标志值 | 含义                                               |
| -------------- | ------ | -------------------------------------------------- |
| ACC_PUBLIC     | 0x0001 | 是否为public类型                                   |
| ACC_FINAL      | 0x0010 | 是否被声明为final，只有类可设置                    |
| ACC_SUPER      | 0x0020 | 是否允许使用invokespecial字节码指令的新语义        |
| ACC_INTERFACE  | 0x0200 | 是否为接口                                         |
| ACC_ABSTARCT   | 0x0400 | 是否为abstract类型，对于接口或抽象类为真，其他为假 |
| ACC_SYNTHETIC  | 0x1000 | 表示该类并非有用户代码产生                         |
| ACC_ANNOTATION | 0X2000 | 表示为注解                                         |
| ACC_ENUM       | 0x4000 | 表示为枚举                                         |

### 类索引、父类索引与接口索引集合

类索引和父类索引都是u2类型的数据，而接口索引集合是一组u2类型的数据集合，父类索引用于确定这个类的父类的权限定名。由于Java语言不允许多重继承，所以父类索引只有一个（除了Object没有）。对于接口索引集合，被实现的接口按照implements语句后的接口顺序依次排列在接口索引集合中。

### 字段表集合

字段表(field_info)用于描述接口或者类中声明的变量。字段(field)包括类级变量以及实例级变量，但不包括在方法内部声明的局部变量。字段叫什么名字、字段被定义为什么数据类型，这些都是无法固定的，只能引用常量池中的常量来描述。

字段表结构：

| 类型 | 名称             | 数量 | 类型           | 名称             | 数量             |
| ---- | ---------------- | ---- | -------------- | ---------------- | ---------------- |
| u2   | access_flags     | 1    | u2             | attributes_count | 1                |
| u2   | name_index       | 1    | attribute_info | attributes       | attributes_count |
| u2   | descriptor_index | 1    |                |                  |                  |

字段修饰放在access_flags项目中，可设置的标志位如下：

| 标志名称      | 标志值 | 含义                   |
| ------------- | ------ | ---------------------- |
| ACC_PULBIC    | 0X0001 | 是否public             |
| ACC_PRIVATE   | 0X0002 | 是否private            |
| ACC_PROTECTED | 0X0004 | 是否protected          |
| ACC_STATIC    | 0X0008 | 是否static             |
| ACC_FINAL     | 0X0010 | 是否final              |
| ACC_VOLATILE  | 0X0040 | 是否volatile           |
| ACC_TRANSIENT | 0X0080 | 是否transient          |
| ACC_SYNTHETIC | 0X1000 | 是否由编译器自动产生的 |
| ACC_ENUM      | 0X4000 | 是否enum               |

跟随access_flags标志的是两项索引值：name_index和descriptor_index。它们都是对常量池的引用，分别代表着字段的简单名称以及字段和方法的描述符。

现在需要解释一下“简单名称”、“描述符”以及前面出现过多次的“全限定名”这三种特殊字符串的概念。

全限定名和简单名称很好理解，以前面的代码为例，“org/fenixsoft/clazz/TestClass”是这个类的全限定名，仅仅是把类全名中的“.”替换成了“/”而已，为了使连续的多个全限定名之间不产生混淆，在使用时最后一般会加入一个“;”表示全限定名结束。简单名称是指没有类型和参数修饰的方法或者字段名称，这个类中的inc()方法和m字段的简单名称分别是“inc”和“m”。

下面是描述符标识字符含义：

| 标识字符 | 含义   | 标识字符 | 含义                            |
| -------- | ------ | -------- | ------------------------------- |
| B        | byte   | J        | long                            |
| C        | char   | S        | short                           |
| D        | double | Z        | boolean                         |
| F        | float  | V        | void                            |
| I        | int    | L        | 对象类型，如`Ljava/lang/Object` |

对于数组类型，每一维度将使用一个前置的“[”字符来描述，如一个定义为`java.lang.String[][]`类型的二维数组，将被记录为：`[[Ljava/lang/String`，一个整型数组`int[]`将被记录为`[I`。

用描述符来描述方法时，按照先参数列表，后返回值的顺序描述，参数列表按照参数的
严格顺序放在一组小括号“()”之内。如方法`void inc()`的描述符为`()V`，方法`java.lang.String.toString()`的描述符为`()Ljava/lang/String;`，方法

```java
int indexOf(char[]source,int sourceOffset,int sourceCount,char[]target,
            int targetOffset,int targetCount,int fromIndex)
```

的描述符为`([CII[CIII)I`。

字段表都包含的固定数据项目到descriptor_index为止就结束了，不过在descriptor_index之后跟随着一个属性表集合用于存储一些额外的信息，字段都可以在属性表中描述零至多项的额外信息。

字段表集合中不会列出从超类或者父接口中继承而来的字段，但有可能列出原本Java代码之中不存在的字段，譬如在内部类中为了保持对外部类的访问性，会自动添加指向外部类实例的字段。

另外,在Java语言中字段是无法重载的，两个字段的数据类型、修饰符不管是否相同，都必须使用不一样的名称，但是对于字节码来讲，如果两个字段的描述符不一致，那字段重名就是合法的。

### 方法表集合

Class文件存储格式中对方法的描述与对字段的描述几乎采用了完全一致的方式，方法表的结构如同字段表一样，依次包括了访问标志(access_flags)、名称索引(name_index)、描述符索引(descriptor_index)、属性表集合(attributes)几项，见下表：

| 类型 | 名称             | 数量 | 类型           | 名称             | 数量             |
| ---- | ---------------- | ---- | -------------- | ---------------- | ---------------- |
| u2   | access_flags     | 1    | u2             | attributes_count | 1                |
| u2   | name_index       | 1    | attribute_info | attributes       | attributes_count |
| u2   | descriptor_index | 1    |                |                  |                  |

至于访问标志位，下表只列出不明显的标志：

| 标志名称    | 标志值 | 含义                           |
| ----------- | ------ | ------------------------------ |
| ACC_SYNCHRONIZED | 0X0020 | 是否为synchronized |
| ACC_BRIDGE  | 0X0040 | 是否为由编译器产生的桥接方法 |
| ACC_VARARGS | 0X0080 | 是否接受不定参数           |
| ACC_STRICTFP | 0X0800 | 是否为strictfp |
| ACC_SYNTHETIC | 0X1000 | 是否由编译器自动产生的 |

与字段表集合相对应的，如果父类方法在子类中没有被重写(Override)，方法表集合中就不会出现来自父类的方法信息。但同样的，有可能会出现由编译器自动添加的方法，最典型的便是类构造器`<clinit>`方法和实例构造器`<init>` 方法。

### 属性表集合

属性表(attribute_info)在前面的讲解之中已经出现过数次，在Class文件、字段表、方法表都可以携带自己的属性表集合，以用于描述某些场景专有的信息。

属性表集合的限制稍微宽松了一些，不再要求各个属性表具有严格顺序，并且只要不与已有属性名重复，任何人
实现的编译器都可以向属性表中写入自己定义的属性信息，Java虚拟机运行时会忽略掉它不认识的属性。

| 属性名称                             | 使用位置           | 含义                                                         |
| ------------------------------------ | ------------------ | ------------------------------------------------------------ |
| Code                                 | 方法表             | Java代码编译成的字节码指令                                   |
| ConstantValue                        | 字段表             | final关键字定义的常量值                                      |
| Deprecated                           | 类、方法表、字段表 | 被声明为deprecated的方法和字段                               |
| Exceptions                           | 方法表             | 方法抛出的异常                                               |
| EnclosingMethod                      | 类文件             | 仅当一个类为局部类或者匿名类时才能拥有这个属性，这个属性用于标示这个类所在的外围方法 |
| InnerClasses                         | 类文件             | 内部类列表                                                   |
| LineNumberTable                      | Code属性           | Java源码的行号与字节码指令的对应关系                         |
| LocalVariableTable                   | Code属性           | 方法的局部变量描述                                           |
| StackMapTable                        | Code属性           | 供新的类型检查验证器（Type Checker）检查和处理目标方法的局部变量和操作数栈所需要的类型是否匹配 |
| Signature                            | 类、方法表、字段表 | 用于支持泛型情况下的方法签名。由于Java的泛型采用擦除法实现，为了避免类型信息被擦除后导致签名混乱，需要这个属性记录泛型中的相关信息 |
| SourceFile                           | 类文件             | 记录源文件名称                                               |
| SourceDebugExtension                 | 类文件             | 用于存储额外的调试信息                                       |
| Synthetic                            | 类、方法表、字段表 | 标识方法或字段为编译器自动生成                               |
| LocalVariableTypeTable               | 类                 | 使用特征签名代替描述符，为了引入泛型语法之后能描述泛型参数化类型而添加的 |
| RuntimeVisibleAnnotations            | 类、方法表、字段表 | 指明哪些注解是运行时可见的                                   |
| RuntimeInvisibleAnnotations          | 类、方法表、字段表 | 指明哪些注解是运行时不可见的                                 |
| RuntimeVisibleParameterAnnotations   | 方法表             | ...                                                          |
| RuntimeInvisibleParameterAnnotations | 方法表             | ...                                                          |
| AnnotatonDefault                     | 方法表             | 记录注解类元素的默认值                                       |
| BootstrapMethods                     | 类文件             | 保存invokedynamic指令引用的引导方法限定符                    |

对于每个属性，它的名称需要从常量池中引用一个CONSTANT_Utf8_info类型的常量来表示，而属性值的结构则是完全自定义的，只需要通过一个u4的长度属性去说明属性值所占用的位数即可。一个符合规则的属性表应该满足下表定义的结构。

| 类型 | 名称                 | 数量             |
| ---- | -------------------- | ---------------- |
| u2   | attribute_name_index | 1                |
| u4   | attribute_length     | 1                |
| u1   | info                 | attribute_length |

